napari_animation/__init__.py
napari_animation/_enum_compat.py
napari_animation/_version.py
napari_animation/animation.py
napari_animation/easing.py
napari_animation/frame_sequence.py
napari_animation/key_frame.py
napari_animation/napari.yaml
napari_animation/utils.py
napari_animation/viewer_state.py
napari_animation/_qt/__init__.py
napari_animation/_qt/animation_widget.py
napari_animation/_qt/frame_widget.py
napari_animation/_qt/keyframelistcontrol_widget.py
napari_animation/_qt/keyframeslist_widget.py
napari_animation/_qt/savedialog_widget.py
napari_animation/_qt/_tests/__init__.py
napari_animation/_qt/_tests/test_animation_widget.py
napari_animation/_tests/__init__.py
napari_animation/_tests/conftest.py
napari_animation/_tests/test_animation.py
napari_animation/_tests/test_easing.py
napari_animation/_tests/test_enum_compat.py
napari_animation/_tests/test_frame_sequence.py
napari_animation/_tests/test_interpolation.py
napari_animation/_tests/test_utils.py
napari_animation/interpolation/__init__.py
napari_animation/interpolation/base_interpolation.py
napari_animation/interpolation/interpolation_constants.py
napari_animation/interpolation/typing.py
napari_animation/interpolation/utils.py
napari_animation/interpolation/viewer_state_interpolation.py
napari_animation-0.0.9.dist-info/licenses/LICENSE
napari_animation-0.0.9.dist-info/METADATA
napari_animation-0.0.9.dist-info/WHEEL
napari_animation-0.0.9.dist-info/entry_points.txt
napari_animation-0.0.9.dist-info/top_level.txt
napari_animation-0.0.9.dist-info/RECORD
