Metadata-Version: 2.4
Name: napari-animation
Version: 0.0.9
Summary: A plugin for making animations in napari
Home-page: https://github.com/napari/napari-animation
Download-URL: https://github.com/napari/napari-animation
Author: Nicholas Sofroniew, Alister Burt, Guillaume Witz, Faris Abouakil, Talley Lambert, napari
License: BSD 3-Clause
Classifier: Development Status :: 3 - Alpha
Classifier: Intended Audience :: Science/Research
Classifier: Topic :: Scientific/Engineering
Classifier: Topic :: Scientific/Engineering :: Visualization
Classifier: Framework :: napari
Classifier: Programming Language :: Python
Classifier: Programming Language :: Python :: 3
Classifier: Programming Language :: Python :: 3.10
Classifier: Programming Language :: Python :: 3.11
Classifier: Programming Language :: Python :: 3.12
Classifier: Programming Language :: Python :: 3.13
Classifier: Operating System :: OS Independent
Classifier: License :: OSI Approved :: BSD License
Requires-Python: >=3.10
License-File: LICENSE
Requires-Dist: imageio
Requires-Dist: imageio-ffmpeg
Requires-Dist: napari>=0.5
Requires-Dist: npe2
Requires-Dist: numpy
Requires-Dist: qtpy
Requires-Dist: scipy
Requires-Dist: tqdm>=4.56.0
Requires-Dist: superqt
Provides-Extra: testing
Requires-Dist: pytest; extra == "testing"
Requires-Dist: pytest-cov; extra == "testing"
Requires-Dist: pytest-qt; extra == "testing"
Requires-Dist: tox; extra == "testing"
Provides-Extra: doc
Requires-Dist: sphinx>6; extra == "doc"
Requires-Dist: sphinx-autobuild; extra == "doc"
Requires-Dist: sphinx-external-toc; extra == "doc"
Requires-Dist: sphinx-copybutton; extra == "doc"
Requires-Dist: sphinx-gallery; extra == "doc"
Requires-Dist: sphinx-favicon; extra == "doc"
Requires-Dist: sphinxcontrib-video; extra == "doc"
Requires-Dist: matplotlib; extra == "doc"
Requires-Dist: myst-nb; extra == "doc"
Requires-Dist: napari-sphinx-theme>=0.3.0; extra == "doc"
Provides-Extra: dev
Requires-Dist: pre-commit; extra == "dev"
Requires-Dist: black; extra == "dev"
Requires-Dist: ruff; extra == "dev"
Requires-Dist: check-manifest; extra == "dev"
Requires-Dist: pytest; extra == "dev"
Requires-Dist: pytest-cov; extra == "dev"
Requires-Dist: pytest-qt; extra == "dev"
Requires-Dist: tox; extra == "dev"
Requires-Dist: sphinx>6; extra == "dev"
Requires-Dist: sphinx-autobuild; extra == "dev"
Requires-Dist: sphinx-external-toc; extra == "dev"
Requires-Dist: sphinx-copybutton; extra == "dev"
Requires-Dist: sphinx-gallery; extra == "dev"
Requires-Dist: sphinx-favicon; extra == "dev"
Requires-Dist: sphinxcontrib-video; extra == "dev"
Requires-Dist: matplotlib; extra == "dev"
Requires-Dist: myst-nb; extra == "dev"
Requires-Dist: napari-sphinx-theme>=0.3.0; extra == "dev"
Dynamic: download-url
Dynamic: license-file
